README.md
setup.py
bin/snpflip
snp_flip/__init__.py
snp_flip/bim_file.py
snp_flip/reference_genome.py
snp_flip/table.py
snp_flip/version.py
snpflip.egg-info/PKG-INFO
snpflip.egg-info/SOURCES.txt
snpflip.egg-info/dependency_links.txt
snpflip.egg-info/requires.txt
snpflip.egg-info/top_level.txt