Metadata-Version: 1.1
Name: snpflip
Version: 0.0.6
Summary: Report reverse and ambiguous strand SNPs.
Home-page: http://github.com/endrebak/snp-flip
Author: Endre Bakken Stovner
Author-email: endrebak@stud.ntnu.no
License: ['GPL-3.0']
Keywords: snp,gwas,strand
Platform: UNKNOWN
Classifier: Programming Language :: Python :: 2.7
Classifier: Programming Language :: Python :: 3
Classifier: Development Status :: 2 - Pre-Alpha
Classifier: Environment :: Other Environment
Classifier: Intended Audience :: Science/Research
Classifier: License :: OSI Approved :: GNU General Public License v3 (GPLv3)
Classifier: Operating System :: POSIX :: Linux
Classifier: Operating System :: MacOS :: MacOS X
Classifier: Topic :: Scientific/Engineering
